amatak_winapp/__init__.py
amatak_winapp/this_init.py
amatak_winapp/winapp.py
amatak_winapp/assets/brand/brand.ico
amatak_winapp/assets/brand/brand.png
amatak_winapp/assets/brand/brand_installer.bmp
amatak_winapp/assets/brand/license_agreement.pdf
amatak_winapp/data/VERSION.txt
amatak_winapp/data/__init__.py
amatak_winapp/gui/__init__.py
amatak_winapp/gui/winapp_gui.py
amatak_winapp/scripts/__init__.py
amatak_winapp/scripts/_init_scanner.py
amatak_winapp/scripts/gen_brand.py
amatak_winapp/scripts/gen_license.py
amatak_winapp/scripts/gen_license_agreement.py
amatak_winapp/scripts/gen_nsi.py
amatak_winapp/scripts/gen_readme.py
amatak_winapp/scripts/gen_tree.py
amatak_winapp/scripts/gen_win.py
amatak_winapp/scripts/winapp_init.py
amatak_winapp-1.0.5.dist-info/licenses/LICENSE
sample-app/__init__.py
sample-app/main.py
sample-app/docs/__init__.py
sample-app/gui/__init__.py
sample-app/src/__init__.py
sample-app/tests/__init__.py
amatak_winapp-1.0.5.dist-info/METADATA
amatak_winapp-1.0.5.dist-info/WHEEL
amatak_winapp-1.0.5.dist-info/entry_points.txt
amatak_winapp-1.0.5.dist-info/top_level.txt
amatak_winapp-1.0.5.dist-info/RECORD
